mcm_label/__init__.py
mcm_label/cli.py
mcm_label/default_print_template.html
mcm_label/default_style.css
mcm_label/default_template.html
mcm_label/mcm_label.py
mcm_label-0.0.2.dist-info/METADATA
mcm_label-0.0.2.dist-info/WHEEL
mcm_label-0.0.2.dist-info/entry_points.txt
mcm_label-0.0.2.dist-info/licenses/LICENSE
mcm_label-0.0.2.dist-info/RECORD
