Metadata-Version: 2.4
Name: mcm-label
Version: 0.0.2
Summary: A command line utility to create scannable labels for McMaster parts
Project-URL: GitHub, https://github.com/a3ng7n/mcm-label
Author-email: Aaron Goldstein <aaron@sirrom.systems>
License-Expression: MIT
License-File: LICENSE
Classifier: Operating System :: OS Independent
Classifier: Programming Language :: Python :: 3
Requires-Python: >=3.12
Requires-Dist: beautifulsoup4>=4.12.3
Requires-Dist: blabel>=0.1.6
Requires-Dist: pymupdf>=1.25.2
Requires-Dist: qrcode[pil]>=8.0
